digitalspot/__init__.py
digitalspot/browser.py
digitalspot/feed.py
digitalspot/robots.py
digitalspot/sitemap.py
DigitalSpot-0.0.1.dist-info/METADATA
DigitalSpot-0.0.1.dist-info/WHEEL
DigitalSpot-0.0.1.dist-info/top_level.txt
DigitalSpot-0.0.1.dist-info/RECORD
